pyqasm/__init__.py
pyqasm/_logging.py
pyqasm/_version.py
pyqasm/analyzer.py
pyqasm/decomposer.py
pyqasm/elements.py
pyqasm/entrypoint.py
pyqasm/exceptions.py
pyqasm/expressions.py
pyqasm/linalg.py
pyqasm/preprocess.py
pyqasm/printer.py
pyqasm/py.typed
pyqasm/scope.py
pyqasm/subroutines.py
pyqasm/transformer.py
pyqasm/validator.py
pyqasm/visitor.py
pyqasm/accelerate/__init__.py
pyqasm/accelerate/linalg.cpython-311-x86_64-linux-gnu.so
pyqasm/accelerate/linalg.pyx
pyqasm/cli/__init__.py
pyqasm/cli/main.py
pyqasm/cli/unroll.py
pyqasm/cli/utils.py
pyqasm/cli/validate.py
pyqasm/maps/__init__.py
pyqasm/maps/decomposition_rules.py
pyqasm/maps/expressions.py
pyqasm/maps/gates.py
pyqasm/modules/__init__.py
pyqasm/modules/base.py
pyqasm/modules/qasm2.py
pyqasm/modules/qasm3.py
pyqasm/pulse/expressions.py
pyqasm/pulse/frame.py
pyqasm/pulse/play.py
pyqasm/pulse/utils.py
pyqasm/pulse/validator.py
pyqasm/pulse/visitor.py
pyqasm/pulse/waveform.py
pyqasm-1.0.0.dist-info/METADATA
pyqasm-1.0.0.dist-info/WHEEL
pyqasm-1.0.0.dist-info/entry_points.txt
pyqasm-1.0.0.dist-info/top_level.txt
pyqasm-1.0.0.dist-info/RECORD
pyqasm-1.0.0.dist-info/licenses/LICENSE
