Metadata-Version: 2.4
Name: pyqasm
Version: 1.0.0
Summary: Python toolkit providing an OpenQASM 3 semantic analyzer and utilities for program analysis and compilation.
Author: qBraid Development Team
Author-email: contact@qbraid.com
License: Apache 2.0
Project-URL: Source Code, https://github.com/qBraid/pyqasm
Project-URL: Bug Tracker, https://github.com/qBraid/pyqasm/issues
Keywords: quantum,openqasm,symantic-analyzer,compiler,qbraid
Classifier: Development Status :: 4 - Beta
Classifier: Intended Audience :: Developers
Classifier: Intended Audience :: Science/Research
Classifier: Natural Language :: English
Classifier: Programming Language :: Python
Classifier: Programming Language :: Python :: 3
Classifier: Programming Language :: Python :: 3.10
Classifier: Programming Language :: Python :: 3.11
Classifier: Programming Language :: Python :: 3.12
Classifier: Programming Language :: Python :: 3.13
Classifier: Programming Language :: Python :: 3 :: Only
Classifier: Topic :: Software Development
Classifier: Topic :: Scientific/Engineering
Classifier: Topic :: Scientific/Engineering :: Physics
Classifier: Typing :: Typed
Classifier: Operating System :: Microsoft :: Windows
Classifier: Operating System :: POSIX
Classifier: Operating System :: Unix
Classifier: Operating System :: MacOS
Requires-Python: >=3.10
License-File: LICENSE
Requires-Dist: numpy
Requires-Dist: openqasm3[parser]<2.0.0,>=1.0.0
Provides-Extra: cli
Requires-Dist: typer>=0.12.1; extra == "cli"
Requires-Dist: rich>=10.11.0; extra == "cli"
Requires-Dist: typing-extensions; extra == "cli"
Provides-Extra: test
Requires-Dist: pytest; extra == "test"
Requires-Dist: pytest-cov; extra == "test"
Requires-Dist: pytest-mpl; extra == "test"
Requires-Dist: pillow<11.4.0; extra == "test"
Requires-Dist: matplotlib; extra == "test"
Requires-Dist: tabulate; extra == "test"
Provides-Extra: lint
Requires-Dist: black; extra == "lint"
Requires-Dist: isort>=6.0.0; extra == "lint"
Requires-Dist: pylint; extra == "lint"
Requires-Dist: mypy; extra == "lint"
Requires-Dist: qbraid-cli>=0.10.2; extra == "lint"
Provides-Extra: docs
Requires-Dist: sphinx<8.3.0,>=7.3.7; extra == "docs"
Requires-Dist: sphinx-autodoc-typehints<3.2,>=1.24; extra == "docs"
Requires-Dist: sphinx-rtd-theme<4.0.0,>=2.0.0; extra == "docs"
Requires-Dist: docutils<0.23; extra == "docs"
Requires-Dist: sphinx-copybutton; extra == "docs"
Provides-Extra: visualization
Requires-Dist: pillow<11.4.0; extra == "visualization"
Requires-Dist: matplotlib; extra == "visualization"
Requires-Dist: tabulate; extra == "visualization"
Provides-Extra: pulse
Requires-Dist: openpulse>=1.0.1; extra == "pulse"
Dynamic: license-file
